torii_boards/__init__.py
torii_boards/_util.py
torii_boards/py.typed
torii_boards/altera/__init__.py
torii_boards/altera/cyclone_iii/__init__.py
torii_boards/altera/cyclone_iii/de0.py
torii_boards/altera/cyclone_iv/__init__.py
torii_boards/altera/cyclone_iv/rz_easyfpga_a2_2.py
torii_boards/altera/cyclone_v/__init__.py
torii_boards/altera/cyclone_v/chameleon96.py
torii_boards/altera/cyclone_v/de0_cv.py
torii_boards/altera/cyclone_v/de10_nano.py
torii_boards/altera/cyclone_v/de1_soc.py
torii_boards/altera/cyclone_v/mister.py
torii_boards/altera/max10/__init__.py
torii_boards/altera/max10/arrow_deca.py
torii_boards/altera/max10/de10_lite.py
torii_boards/gowin/__init__.py
torii_boards/gowin/gw1n/__init__.py
torii_boards/gowin/gw1n/tang_nano.py
torii_boards/lattice/__init__.py
torii_boards/lattice/ecp5/__init__.py
torii_boards/lattice/ecp5/colorlight_5a75b_r7_0.py
torii_boards/lattice/ecp5/ecp5_5g_evn.py
torii_boards/lattice/ecp5/ecpix5.py
torii_boards/lattice/ecp5/logicbone.py
torii_boards/lattice/ecp5/orangecrab_r0_1.py
torii_boards/lattice/ecp5/orangecrab_r0_2.py
torii_boards/lattice/ecp5/supercon19badge.py
torii_boards/lattice/ecp5/ulx3s.py
torii_boards/lattice/ecp5/versa_ecp5.py
torii_boards/lattice/ecp5/versa_ecp5_5g.py
torii_boards/lattice/ice40/__init__.py
torii_boards/lattice/ice40/blackice.py
torii_boards/lattice/ice40/blackice_ii.py
torii_boards/lattice/ice40/fomu_hacker.py
torii_boards/lattice/ice40/fomu_pvt.py
torii_boards/lattice/ice40/ice40_hx1k_blink_evn.py
torii_boards/lattice/ice40/ice40_hx8k_b_evn.py
torii_boards/lattice/ice40/ice40_up5k_b_evn.py
torii_boards/lattice/ice40/icebreaker.py
torii_boards/lattice/ice40/icebreaker_bitsy.py
torii_boards/lattice/ice40/icestick.py
torii_boards/lattice/ice40/icesugar.py
torii_boards/lattice/ice40/icesugar_nano.py
torii_boards/lattice/ice40/nandland_go.py
torii_boards/lattice/ice40/tinyfpga_bx.py
torii_boards/lattice/ice40/upduino_v1.py
torii_boards/lattice/ice40/upduino_v2.py
torii_boards-0.8.1.dist-info/licenses/LICENSE
torii_boards-0.8.1.dist-info/licenses/LICENSE.docs
torii_boards-0.8.1.dist-info/METADATA
torii_boards-0.8.1.dist-info/WHEEL
torii_boards-0.8.1.dist-info/top_level.txt
torii_boards-0.8.1.dist-info/RECORD
