Metadata-Version: 2.4
Name: torii-boards
Version: 0.8.1
Summary: Supplementary FPGA Board Files for Torii
Author: Torii Contributors
Author-email: Aki Van Ness <aki@lethalbit.net>, Rachel Mant <git@dragonmux.network>
License-Expression: BSD-2-Clause
Project-URL: source, https://github.com/shrine-maiden-heavy-industries/torii-boards
Project-URL: issues, https://github.com/shrine-maiden-heavy-industries/torii-boards/issues
Project-URL: documentation, https://torii-boards.shmdn.link
Project-URL: changelog, https://torii-boards.shmdn.link/changelog.html
Keywords: Torii,HDL,FPGA
Classifier: Development Status :: 4 - Beta
Classifier: Intended Audience :: Developers
Classifier: Intended Audience :: Education
Classifier: Intended Audience :: Information Technology
Classifier: Intended Audience :: Science/Research
Classifier: Operating System :: MacOS :: MacOS X
Classifier: Operating System :: Microsoft :: Windows
Classifier: Operating System :: POSIX :: Linux
Classifier: Programming Language :: Python :: 3.11
Classifier: Programming Language :: Python :: 3.12
Classifier: Programming Language :: Python :: 3.13
Classifier: Programming Language :: Python :: 3.14
Classifier: Programming Language :: Python :: Implementation :: CPython
Classifier: Programming Language :: Python :: Implementation :: PyPy
Classifier: Topic :: Scientific/Engineering
Classifier: Topic :: Scientific/Engineering :: Electronic Design Automation (EDA)
Classifier: Topic :: Software Development
Classifier: Topic :: Software Development :: Embedded Systems
Classifier: Topic :: Software Development :: Libraries
Classifier: Typing :: Typed
Requires-Python: >=3.11
License-File: LICENSE
License-File: LICENSE.docs
Requires-Dist: torii<1.0,>=0.8.0
Provides-Extra: dev
Requires-Dist: nox; extra == "dev"
Dynamic: license-file
